jupyterlab_cube/__init__.py
jupyterlab_cube/_version.py
jupyterlab_cube/labextension/build_log.json
jupyterlab_cube/labextension/package.json
jupyterlab_cube/labextension/static/90f06476859102392bd8226d3b0700e8.svg
jupyterlab_cube/labextension/static/lib_index_js.67be042ab5c276f40aca.js
jupyterlab_cube/labextension/static/lib_index_js.67be042ab5c276f40aca.js.map
jupyterlab_cube/labextension/static/remoteEntry.76730482eeb38dbe1300.js
jupyterlab_cube/labextension/static/remoteEntry.76730482eeb38dbe1300.js.map
jupyterlab_cube/labextension/static/style.js
jupyterlab_cube/labextension/static/style_index_css.e0ad3facc16023874e5c.js
jupyterlab_cube/labextension/static/style_index_css.e0ad3facc16023874e5c.js.map
jupyterlab_cube/labextension/static/vendors-node_modules_css-loader_dist_runtime_api_js-node_modules_css-loader_dist_runtime_cssW-313cda.264a7594652a3aaa33f8.js
jupyterlab_cube/labextension/static/vendors-node_modules_css-loader_dist_runtime_api_js-node_modules_css-loader_dist_runtime_cssW-313cda.264a7594652a3aaa33f8.js.map
jupyterlab_cube/labextension/static/vendors-node_modules_material-ui-color_esm_index_js.f92072dd2d8a22078e34.js
jupyterlab_cube/labextension/static/vendors-node_modules_material-ui-color_esm_index_js.f92072dd2d8a22078e34.js.map
jupyterlab_cube/labextension/static/vendors-node_modules_material-ui_core_esm_Button_Button_js-node_modules_material-ui_core_esm_-53abab.75eb4a16f289c42f8f7d.js
jupyterlab_cube/labextension/static/vendors-node_modules_material-ui_core_esm_Button_Button_js-node_modules_material-ui_core_esm_-53abab.75eb4a16f289c42f8f7d.js.map
jupyterlab_cube/labextension/static/vendors-node_modules_material-ui_core_esm_FormControlLabel_FormControlLabel_js-node_modules_m-404079.536f98c2ccb808169432.js
jupyterlab_cube/labextension/static/vendors-node_modules_material-ui_core_esm_FormControlLabel_FormControlLabel_js-node_modules_m-404079.536f98c2ccb808169432.js.map
jupyterlab_cube-0.1.9.dist-info/LICENSE
jupyterlab_cube-0.1.9.dist-info/METADATA
jupyterlab_cube-0.1.9.dist-info/WHEEL
jupyterlab_cube-0.1.9.dist-info/top_level.txt
jupyterlab_cube-0.1.9.dist-info/RECORD
