Metadata-Version: 2.1
Name: jupyterlab-cube
Version: 0.1.9
Summary: A JupyterLab extension for rendering cube files.
Home-page: https://github.com/osscar-org/jupyterlab-cube
Author: Dou Du
License: BSD-3-Clause
Keywords: Jupyter,JupyterLab
Platform: Linux
Platform: Mac OS X
Platform: Windows
Classifier: License :: OSI Approved :: BSD License
Classifier: Programming Language :: Python
Classifier: Programming Language :: Python :: 3
Classifier: Programming Language :: Python :: 3.6
Classifier: Programming Language :: Python :: 3.7
Classifier: Programming Language :: Python :: 3.8
Classifier: Framework :: Jupyter
Requires-Python: >=3.6
License-File: LICENSE
Requires-Dist: jupyterlab (~=3.0)
